co2_tracker_utils/__init__.py
co2_tracker_utils/cloud_logging.py
co2_tracker_utils/gpu_logging.py
co2_tracker_utils-0.1.0.dist-info/LICENSE
co2_tracker_utils-0.1.0.dist-info/METADATA
co2_tracker_utils-0.1.0.dist-info/WHEEL
co2_tracker_utils-0.1.0.dist-info/top_level.txt
co2_tracker_utils-0.1.0.dist-info/RECORD
