Metadata-Version: 2.1
Name: co2-tracker-utils
Version: 0.1.0
Summary: CO2 Tracker helpers
Home-page: https://github.com/comet-ml/co2-tracker-utils
Author: Boris Feld
Author-email: boris@comet.ml
License: MIT license
Keywords: co2-tracker-utils
Platform: UNKNOWN
Classifier: Development Status :: 2 - Pre-Alpha
Classifier: Intended Audience :: Developers
Classifier: License :: OSI Approved :: MIT License
Classifier: Natural Language :: English
Classifier: Programming Language :: Python :: 3
Classifier: Programming Language :: Python :: 3.5
Classifier: Programming Language :: Python :: 3.6
Classifier: Programming Language :: Python :: 3.7
Classifier: Programming Language :: Python :: 3.8
Requires-Dist: nvidia-ml-py3 (==7.352.0)
Requires-Dist: requests (>=2.18.4)
Requires-Dist: typing (>=3.7.4) ; python_version < "3.5"
